bashify.py
bashify-0.1.4.dist-info/LICENSE
bashify-0.1.4.dist-info/METADATA
bashify-0.1.4.dist-info/WHEEL
bashify-0.1.4.dist-info/top_level.txt
bashify-0.1.4.dist-info/RECORD
