Metadata-Version: 2.1
Name: bashify
Version: 0.1.4
Summary: A package to print and execture bash files
Home-page: https://github.com/UniWrighte/bashify
Author: David Kamer
Author-email: me@davidkamer.com
License: UNKNOWN
Platform: UNKNOWN
Classifier: Programming Language :: Python :: 3
Classifier: License :: OSI Approved :: MIT License
Classifier: Operating System :: OS Independent
